faster_requests/__init__.py
faster_requests-0.1.1.dist-info/LICENSE
faster_requests-0.1.1.dist-info/METADATA
faster_requests-0.1.1.dist-info/WHEEL
faster_requests-0.1.1.dist-info/top_level.txt
faster_requests-0.1.1.dist-info/RECORD
