Metadata-Version: 2.1
Name: faster-requests
Version: 0.1.1
Summary: Faster requests for Python 3
Home-page: UNKNOWN
Author: Dropout
License: UNKNOWN
Keywords: python,requests,fast requests,faster requests
Platform: UNKNOWN
Classifier: Intended Audience :: Developers
Classifier: Programming Language :: Python :: 3
Classifier: Operating System :: Unix
Classifier: Operating System :: MacOS :: MacOS X
Classifier: Operating System :: Microsoft :: Windows
License-File: LICENSE
